{
  "GLADIUS-GLADIUS.aromaPrinciple": "Lore",
  "GLADIUS-GLADIUS.banter.alive.endTurnPing": "Co-op hurry up end turn ping message",
  "GLADIUS-GLADIUS.banter.dead.endTurnPing": "...",
  "GLADIUS-GLADIUS.cardsModifierDescription": "Gladius cards will now appear in rewards and shops.",
  "GLADIUS-GLADIUS.cardsModifierTitle": "Gladius Cards",
  "GLADIUS-GLADIUS.description": "Character Selection\nScreen Description",
  "GLADIUS-GLADIUS.eventDeathPrevention": "Co-op survival line",
  "GLADIUS-GLADIUS.goldMonologue": "Line spoken when obtaining a large amount of gold",
  "GLADIUS-GLADIUS.possessiveAdjective": "his",
  "GLADIUS-GLADIUS.pronounObject": "him",
  "GLADIUS-GLADIUS.pronounPossessive": "his",
  "GLADIUS-GLADIUS.pronounSubject": "he",
  "GLADIUS-GLADIUS.title": "Gladius",
  "GLADIUS-GLADIUS.titleObject": "Gladius"
}